LingJichuXuePythonDierBan/README.md
LingJichuXuePythonDierBan/__init__.py
LingJichuXuePythonDierBan/__main__.py
LingJichuXuePythonDierBan/file.epub
LingJichuXuePythonDierBan/index.html
LingJichuXuePythonDierBan/css/__init__.py
LingJichuXuePythonDierBan/css/annotations.css
LingJichuXuePythonDierBan/css/main.css
LingJichuXuePythonDierBan/css/normalize.css
LingJichuXuePythonDierBan/css/popup.css
LingJichuXuePythonDierBan/font/__init__.py
LingJichuXuePythonDierBan/font/fontello.eot
LingJichuXuePythonDierBan/font/fontello.svg
LingJichuXuePythonDierBan/font/fontello.ttf
LingJichuXuePythonDierBan/font/fontello.woff
LingJichuXuePythonDierBan/img/__init__.py
LingJichuXuePythonDierBan/img/annotator-glyph-sprite.png
LingJichuXuePythonDierBan/img/annotator-icon-sprite.png
LingJichuXuePythonDierBan/img/apple-touch-icon.png
LingJichuXuePythonDierBan/img/cancelfullscreen.png
LingJichuXuePythonDierBan/img/close.png
LingJichuXuePythonDierBan/img/fullscreen.png
LingJichuXuePythonDierBan/img/loader.gif
LingJichuXuePythonDierBan/img/menu-icon.png
LingJichuXuePythonDierBan/img/save.png
LingJichuXuePythonDierBan/img/saved.png
LingJichuXuePythonDierBan/img/settings-s.png
LingJichuXuePythonDierBan/img/settings.png
LingJichuXuePythonDierBan/img/star.png
LingJichuXuePythonDierBan/js/__init__.py
LingJichuXuePythonDierBan/js/epub.js
LingJichuXuePythonDierBan/js/epub.min.js
LingJichuXuePythonDierBan/js/epub.min.map
LingJichuXuePythonDierBan/js/hooks.min.js
LingJichuXuePythonDierBan/js/hooks.min.map
LingJichuXuePythonDierBan/js/reader.js
LingJichuXuePythonDierBan/js/reader.js.map
LingJichuXuePythonDierBan/js/reader.min.js
LingJichuXuePythonDierBan/js/reader.min.map
LingJichuXuePythonDierBan/js/hooks/__init__.py
LingJichuXuePythonDierBan/js/hooks/extensions/__init__.py
LingJichuXuePythonDierBan/js/hooks/extensions/highlight.js
LingJichuXuePythonDierBan/js/libs/__init__.py
LingJichuXuePythonDierBan/js/libs/jquery.min.js
LingJichuXuePythonDierBan/js/libs/localforage.min.js
ling_jichu_xue_python_dier_ban-2024.3.2.0.dist-info/METADATA
ling_jichu_xue_python_dier_ban-2024.3.2.0.dist-info/WHEEL
ling_jichu_xue_python_dier_ban-2024.3.2.0.dist-info/entry_points.txt
ling_jichu_xue_python_dier_ban-2024.3.2.0.dist-info/top_level.txt
ling_jichu_xue_python_dier_ban-2024.3.2.0.dist-info/RECORD
